cms7/mdext.py
cms7/error.py
cms7/hyphenate.py
cms7/__main__.py
cms7/__init__.py
cms7/source.py
cms7/generator.py
cms7/resources.py
cms7/util.py
cms7/cli.py
cms7/config.py
cms7/modules/faq.py
cms7/modules/__init__.py
cms7/modules/feed.py
cms7/modules/pages.py
cms7/modules/null.py
cms7/modules/blog.py
cms7-0.1a21.dist-info/entry_points.txt
cms7-0.1a21.dist-info/WHEEL
cms7-0.1a21.dist-info/top_level.txt
cms7-0.1a21.dist-info/DESCRIPTION.rst
cms7-0.1a21.dist-info/metadata.json
cms7-0.1a21.dist-info/METADATA
cms7-0.1a21.dist-info/RECORD
