Metadata-Version: 2.0
Name: cms7
Version: 0.1a21
Summary: Simple static site generator
Home-page: https://github.com/freenode/cms7
Author: Ed Kellett
Author-email: e@kellett.im
License: UNKNOWN
Platform: UNKNOWN
Classifier: Development Status :: 3 - Alpha
Classifier: Programming Language :: Python :: 3
Classifier: Programming Language :: Python :: 3.4
Classifier: Programming Language :: Python :: 3.5
Requires-Dist: colorlog
Requires-Dist: clize
Requires-Dist: feedgenerator
Requires-Dist: html5lib
Requires-Dist: jinja2
Requires-Dist: markdown
Requires-Dist: requests
Requires-Dist: pathlib2
Requires-Dist: python-dateutil
Requires-Dist: pyyaml
